jumichica/__init__.py
mkdocs_jumichica_theme-0.0.2.dist-info/LICENSE
mkdocs_jumichica_theme-0.0.2.dist-info/METADATA
mkdocs_jumichica_theme-0.0.2.dist-info/WHEEL
mkdocs_jumichica_theme-0.0.2.dist-info/entry_points.txt
mkdocs_jumichica_theme-0.0.2.dist-info/top_level.txt
mkdocs_jumichica_theme-0.0.2.dist-info/RECORD
